.flake8
.gitignore
.travis.yml
LICENSE.txt
README.md
requirements-dev.txt
requirements.txt
setup.py
cidades/ariss.md
cidades/betha.md
cidades/dsf.md
cidades/ginfes.md
cidades/issintel.md
cidades/issnet.md
cidades/saatri.md
cidades/simpliss.md
cidades/susesu.md
cidades/webiss.md
docs/Makefile
docs/conf.py
docs/index.rst
docs/make.bat
odoonfe3.egg-info/PKG-INFO
odoonfe3.egg-info/SOURCES.txt
odoonfe3.egg-info/dependency_links.txt
odoonfe3.egg-info/requires.txt
odoonfe3.egg-info/top_level.txt
pytrustnfe/Servidores.py
pytrustnfe/__init__.py
pytrustnfe/certificado.py
pytrustnfe/client.py
pytrustnfe/exceptions.py
pytrustnfe/urls.py
pytrustnfe/utils.py
pytrustnfe/nfe/__init__.py
pytrustnfe/nfe/assinatura.py
pytrustnfe/nfe/danfce.py
pytrustnfe/nfe/danfe.py
pytrustnfe/nfe/patch.py
pytrustnfe/nfe/fonts/NimbusSanL Bold.ttf
pytrustnfe/nfe/fonts/NimbusSanL Regular.ttf
pytrustnfe/nfe/templates/NFeDistribuicaoDFe.xml
pytrustnfe/nfe/templates/NfeAutorizacao.xml
pytrustnfe/nfe/templates/NfeConsultaCadastro.xml
pytrustnfe/nfe/templates/NfeConsultaDest.xml
pytrustnfe/nfe/templates/NfeConsultaProtocolo.xml
pytrustnfe/nfe/templates/NfeInutilizacao.xml
pytrustnfe/nfe/templates/NfeRetAutorizacao.xml
pytrustnfe/nfe/templates/NfeStatusServico.xml
pytrustnfe/nfe/templates/RecepcaoEvento.xml
pytrustnfe/nfe/templates/RecepcaoEventoManifesto.xml
pytrustnfe/nfse/__init__.py
pytrustnfe/nfse/assinatura.py
pytrustnfe/nfse/aparecida/__init__.py
pytrustnfe/nfse/aparecida/templates/Rps.xml
pytrustnfe/nfse/aparecida/templates/cancelarNfse.xml
pytrustnfe/nfse/aparecida/templates/consultarLoteRps.xml
pytrustnfe/nfse/aparecida/templates/recepcionarLoteRps.xml
pytrustnfe/nfse/betha/__init__.py
pytrustnfe/nfse/betha/templates/CancelarNfse.xml
pytrustnfe/nfse/betha/templates/ConsultarLoteRps.xml
pytrustnfe/nfse/betha/templates/ConsultarNfseFaixa.xml
pytrustnfe/nfse/betha/templates/ConsultarNfsePorRps.xml
pytrustnfe/nfse/betha/templates/ConsultarNfseServicoPrestado.xml
pytrustnfe/nfse/betha/templates/ConsultarNfseServicoTomado.xml
pytrustnfe/nfse/betha/templates/GerarNfse.xml
pytrustnfe/nfse/betha/templates/RecepcionarLoteRps.xml
